sub/src/line_gen.sv
`timescale 1ns / 1ps
`default_nettype none

module line_gen (
    input wire clk_in, //system clock
    input wire rst_in, //system reset

    input wire data_valid_in, // 1

    input wire signed [31:0] x_in,
    input wire signed [31:0] y_in,
    input wire [3:0] color_in,

    output logic signed [31:0] x_start_test,
    output logic signed [31:0] y_start_test,
    output logic signed [31:0] x_end_test,
    output logic signed [31:0] y_end_test,

    output logic signed [31:0] x, //current hcount being read
    output logic signed [31:0] y, //current vcount being read
    output logic [3:0] color, //current vcount being read
    output logic next_point
  );

  logic signed [31:0] x_start;
  logic signed [31:0] y_start;

  logic signed [31:0] x_end;
  logic signed [31:0] y_end;
  logic signed [3:0] color_end;

  assign x_start_test = x_start;
  assign y_start_test = y_start;
  assign x_end_test = x_end;
  assign y_end_test = y_end;

  logic has_first_point;
  logic signed [31:0] dx;
  logic signed [31:0] dy;
  logic sx, sy;
  logic signed [31:0] err;
  enum {IDLE, DRAWING} state;

  // assign test_display = {3'b0, state, 3'b0, has_first_point, 3'b0, next_point, x_end, y_end >>> 3};
  // assign test_display = {3'b0, state, 3'b0, has_first_point, 3'b0, next_point, x_end, y_end >>> 3};
  // assign test_display = {x_end, 1'b0, y_end};
  // assign test_display = {x_start, 1'b0, y_start};

  always_ff @(posedge clk_in)begin
    if (rst_in) begin
      dx <= 0;
      dy <= 0;
      sx <= 1;
      sy <= 1;
      err <= 0;
      x<=0;
      y<=0;
      state <= IDLE;
      has_first_point <= 0;
      next_point <= 0;
    end else begin
    case(state)
      DRAWING: begin
        next_point <= 0;
        //if we have reached the end of the line stop drawing
        if(x_end==x && y_end==y)begin
          state <= IDLE;
        //need this case due to verilog quirk
        end else if (2*err>=dy && 2*err<=dx) begin
          x <= sx ? x+1 : x-1;
          y <= sy ? y+1 : y-1;
          err <= err + dx + dy;
        end else if(2*err>=dy) begin
          x <= sx ? x+1 : x-1;
          err <= err + dy;
        end else if(2*err<=dx) begin
          y <= sy ? y + 1 : y - 1;
          err <= err + dx;
        end
      end
      default: begin
        if(data_valid_in)begin
          if (!has_first_point) begin
            has_first_point <= 1;
            x_end <= x_in;
            y_end <= y_in;
            color <= color_in;
          end else begin
            next_point <= 1;
            state <= DRAWING;
            //calculate current deltas
            dx = x_in>x_end ? $signed(x_in)-$signed(x_end) : $signed(x_end)-$signed(x_in);
            sx = x_end<x_in ? 1 : 0;
            dy = y_in>y_end ? $signed(y_end)-$signed(y_in) : $signed(y_in)-$signed(y_end);
            sy = y_end<y_in ? 1 : 0;
            err <= (x_in>x_end ? $signed(x_in)-$signed(x_end) : $signed(x_end)-$signed(x_in)) + (y_in>y_end ? $signed(y_end)-$signed(y_in) : $signed(y_in)-$signed(y_end));
            x <= x_end;
            y <= y_end;
            x_end <= x_in;
            y_end <= y_in;
            color_end <= color_in;
            x_start <= x_end;
            y_start <= y_end;
            color <= color_end;
          end
        end //else begin
        //   has_first_point<=1'b0;
        // end
      end
    endcase
    end
  end
endmodule
`default_nettype wire

sub/src/projection.sv
`timescale 1ns / 1ps
`default_nettype none


module projection #(
      parameter N_TRACKING_POINTS=4,
      parameter N_VIRTUAL_POINTS=8
    ) (
    input wire clk_in, //system clock
    input wire rst_in, //system reset

    input wire signed [N_TRACKING_POINTS - 2:0][15:0] x_vec,
    input wire signed [N_TRACKING_POINTS - 2:0][15:0] y_vec,

    input wire signed [N_TRACKING_POINTS - 2:0][15:0] point_scalars,
    input wire [3:0] point_color,

    input wire [10:0] x_origin,
    input wire [9:0] y_origin,

    output logic signed [31:0] x_proj,
    output logic signed [31:0] y_proj,

    output logic [3:0] color_proj
  );

  logic [$clog2(N_VIRTUAL_POINTS) - 1:0] index;

  always_ff @(posedge clk_in) begin
    if (rst_in) begin
      index <= 0;
      x_proj <= 0;
      y_proj <= 0;
      color_proj <= 0;
    end else begin
        x_proj <= ((($signed({x_vec[0],8'b0})*$signed(point_scalars[0]))>>>16)+
                  (($signed({x_vec[1],8'b0})*$signed(point_scalars[1]))>>>16)+
                  (($signed({x_vec[2],8'b0})*$signed(point_scalars[2]))>>>16))+$signed({1'b0,x_origin});
        y_proj <= ((($signed({y_vec[0],8'b0})*$signed(point_scalars[0]))>>>16)+
                  (($signed({y_vec[1],8'b0})*$signed(point_scalars[1]))>>>16)+
                  (($signed({y_vec[2],8'b0})*$signed(point_scalars[2]))>>>16))+$signed({1'b0,y_origin});
        color_proj <= point_color;
    end
  end


endmodule


`default_nettype wire

sub/src/vectors.sv
`timescale 1ns / 1ps
`default_nettype none

module vectors #(
      parameter N_TRACKING_POINTS=4,
      parameter N_VIRTUAL_POINTS=449608
    ) (
    input wire clk_in, //system clock
    input wire rst_in, //system reset

    input wire [10:0] red_x_com,
    input wire [9:0] red_y_com,
    input wire [10:0] purple_x_com,
    input wire [9:0] purple_y_com,
    input wire [10:0] green_x_com,
    input wire [9:0] green_y_com,
    input wire [10:0] blue_x_com,
    input wire [9:0] blue_y_com,
    input wire valid_blue,
    input wire valid_red,
    input wire valid_green,
    input wire valid_purple,

    output logic signed [N_TRACKING_POINTS - 2:0][15:0] ball_vectors_x,
    output logic signed [N_TRACKING_POINTS - 2:0][15:0] ball_vectors_y,

    output logic [10:0] red_x_stored,
    output logic [9:0] red_y_stored,
    output logic [10:0] blue_x_stored,
    output logic [9:0] blue_y_stored,
    output logic [10:0] purple_x_stored,
    output logic [9:0] purple_y_stored,
    output logic [10:0] green_x_stored,
    output logic [9:0] green_y_stored
  );

    logic has_green, has_red, has_purple, has_blue;
  //Center of Mass variables
  enum {IDLE, CALCULATING} state;

  always_ff @(posedge clk_in)begin
     if (rst_in)begin
        ball_vectors_x <= 0;
        ball_vectors_y <= 0;
     end else begin
        case(state)
            CALCULATING: begin
                state<=IDLE;
                ball_vectors_x[0] <= $signed({1'b0,green_x_stored}) - $signed({1'b0,red_x_stored});
                ball_vectors_y[0] <= $signed({1'b0,green_y_stored}) - $signed({1'b0,red_y_stored});
                ball_vectors_x[1] <= $signed({1'b0,blue_x_stored}) - $signed({1'b0,red_x_stored});
                ball_vectors_y[1] <= $signed({1'b0,blue_y_stored}) - $signed({1'b0,red_y_stored});
                ball_vectors_x[2] <= $signed({1'b0,purple_x_stored}) - $signed({1'b0,red_x_stored});
                ball_vectors_y[2] <= $signed({1'b0,purple_y_stored}) - $signed({1'b0,red_y_stored});
            end
            default: begin
                if (has_green && has_blue && has_red && has_purple)begin
                    state<=CALCULATING;
                    has_green<=0;
                    has_blue<=0;
                    has_purple<=0;
                    has_red<=0;
                end else begin
                    if(valid_red)begin
                    red_x_stored<=red_x_com;
                    red_y_stored<=red_y_com;
                    has_red<=1;
                    end
                    if(valid_blue)begin
                        blue_x_stored<=blue_x_com;
                        blue_y_stored<=blue_y_com;
                        has_blue<=1;
                    end
                    if(valid_purple)begin
                        purple_x_stored<=purple_x_com;
                        purple_y_stored<=purple_y_com;
                        has_purple<=1;
                    end
                    if(valid_green)begin
                        green_x_stored<=green_x_com;
                        green_y_stored<=green_y_com;
                        has_green<=1;
                    end
                end
            end
        endcase
    end
  end


endmodule


`default_nettype wire

sub/sim/projection_tb.sv
`timescale 1ns / 1ps
`default_nettype none

module projection_tb;

    //make logics for inputs and outputs!
    localparam N_TRACKING_POINTS=4;

    logic clk_in;
    logic rst_in;

    // logic signed [N_TRACKING_POINTS - 2:0][15:0] x_vec;
    // logic signed [N_TRACKING_POINTS - 2:0][15:0] y_vec;
    logic signed [N_TRACKING_POINTS - 2:0][15:0] point_scalars;


    logic [10:0] red_x_com;
    logic [9:0] red_y_com;
    logic [10:0] purple_x_com;
    logic [9:0] purple_y_com;
    logic [10:0] green_x_com;
    logic [9:0] green_y_com;
    logic [10:0] blue_x_com;
    logic [9:0] blue_y_com;
    logic valid_blue;
    logic valid_red;
    logic valid_green;
    logic valid_purple;

    logic signed [2:0][15:0] ball_vectors_x;
    logic signed [2:0][15:0] ball_vectors_y;

    vectors uut1(
            .clk_in(clk_in), .rst_in(rst_in),
            .red_x_com(red_x_com),
            .red_y_com(red_y_com),
            .purple_x_com(purple_x_com),
            .purple_y_com(purple_y_com),
            .green_x_com(green_x_com),
            .green_y_com(green_y_com),
            .blue_x_com(blue_x_com),
            .blue_y_com(blue_y_com),
            .valid_blue(valid_blue),
            .valid_red(valid_red),
            .valid_green(valid_green),
            .valid_purple(valid_purple),
            .ball_vectors_x(ball_vectors_x),
            .ball_vectors_y(ball_vectors_y)
            );

    logic signed [31:0] x_proj;
    logic signed [31:0] y_proj;
    logic signed [31:0] test_val;
    logic signed [10:0] other_val;
    logic [3:0] point_color;
    logic [3:0] color_proj;

    logic signed [31:0] x; //current hcount being read
    logic signed [31:0] y;

    projection uut(.clk_in(clk_in), .rst_in(rst_in),
                .x_vec(ball_vectors_x),
                .y_vec(ball_vectors_y),
                .x_origin(red_x_com),
                .point_color(point_color),
                .y_origin(red_y_com),
                .point_scalars(point_scalars),
                .x_proj(x_proj),
                .y_proj(y_proj),
                .color_proj(color_proj));


    line_gen uut2(.clk_in(clk_in), .rst_in(rst_in),
                    .x_in(x_proj),
                    .y_in(y_proj),
                    .color_in(color_proj),
                    .data_valid_in(1'b1),
                    .x(x),
                    .y(y));



    always begin
        #5;  //every 5 ns switch...so period of clock is 10 ns...100 MHz clock
        clk_in = !clk_in;
    end

    //initial block...this is our test simulation
    initial begin
        $dumpfile("projection.vcd"); //file to store value change dump (vcd)
        $dumpvars(0,projection_tb); //store everything at the current level and below
        $display("Starting Sim"); //print nice message
        clk_in = 0; //initialize clk (super important)
        rst_in = 0; //initialize rst (super important)
        point_color = 4'd1;
        point_scalars = {16'h0300, 16'h0000, 16'h0000};
        red_x_com<=0;
        red_y_com<=0;
        #10  //wait a little bit of time at beginning
        rst_in = 1; //reset system
        #10; //hold high for a few clock cycles
        rst_in=0;
        // #10;

        // x_vec = {16'b1111111111111101, 16'b1111111111111000, 16'b1111111111110111};

        #10
        valid_blue=1;
        valid_red=1;
        valid_green=1;
        valid_purple=1;
        red_x_com=11'd300;
        red_y_com=10'd300;
        purple_x_com=11'd300;
        purple_y_com=10'd200;
        green_x_com=11'd400;
        green_y_com=10'd300;
        blue_x_com=11'd250;
        blue_y_com=10'd350;
        #10;
        valid_blue=0;
        valid_red=0;
        valid_green=0;
        valid_purple=0;
        #10

        #100

        // test_val =  (((x_vec[0]<<<8)*point_scalars[0])>>>16)+
        //             (((x_vec[1]<<<8)*point_scalars[1])>>>16)
        //             +((x_vec[2]<<<8)* (point_scalars[2])>>>16)+$signed({1'b0,x_origin});
        // #10
        // other_val=((((x_vec[0]<<<8 * point_scalars[0])>>>16) +
        //             ((x_vec[1]<<<8 * point_scalars[1])>>>16) +
        //             ((x_vec[2]<<<8 * point_scalars[2])>>>16))) + $signed({1'b0, x_origin});
        // other_val=$signed(test_val)+$signed({1'b0,y_origin});

        // x_vec = {16'h00_03, 16'h00_08, 16'h00_09};
        // y_vec = {16'h00_05, 16'h00_02, 16'h00_04};

        // Testing a 1000 x's and y's
        // for (int i = 0; i<1000; i= i+1)begin
        //   x_in = i;
        //   y_in = i/2;
        //   valid_in = 1;
        //   #10;
        // end
        // valid_in = 0;
        // #100;
        // tabulate_in = 1;
        // #10;
        // tabulate_in = 0;
        // #10000;

        // // Testing just one frame
        // x_in = 111;
        // y_in = 333;
        // valid_in = 1;
        // #10;
        // valid_in = 0;
        // #100;
        // tabulate_in = 1;
        // #10;
        // tabulate_in = 0;
        // #10000;

        // // Testing 1024 x 768 valid pixels
        // for (int i = 0; i<1024; i= i+1)begin
        //   for (int j = 0; j<768; j= j+1)begin
        //     x_in = i;
        //     y_in = j;
        //     valid_in = 1;
        //     #10;
        //   end
        // end
        // valid_in = 0;
        // #100;
        // tabulate_in = 1;
        // #10;
        // tabulate_in = 0;
        // #10000;

        // // Testing no valid pixels
        // tabulate_in = 1;
        // #10;
        // tabulate_in = 0;
        #10000;

        $display("Finishing Sim"); //print nice message
        $finish;

    end
endmodule //counter_tb

`default_nettype wire

sub/projection.vcd
$date
	Mon Dec 12 15:14:45 2022
$end
$version
	Icarus Verilog
$end
$timescale
	1ps
$end
$scope module projection_tb $end
$var wire 32 ! y_proj [31:0] $end
$var wire 32 " y [31:0] $end
$var wire 32 # x_proj [31:0] $end
$var wire 32 $ x [31:0] $end
$var wire 4 % color_proj [3:0] $end
$var wire 48 & ball_vectors_y [47:0] $end
$var wire 48 ' ball_vectors_x [47:0] $end
$var reg 11 ( blue_x_com [10:0] $end
$var reg 10 ) blue_y_com [9:0] $end
$var reg 1 * clk_in $end
$var reg 11 + green_x_com [10:0] $end
$var reg 10 , green_y_com [9:0] $end
$var reg 4 - point_color [3:0] $end
$var reg 48 . point_scalars [47:0] $end
$var reg 11 / purple_x_com [10:0] $end
$var reg 10 0 purple_y_com [9:0] $end
$var reg 11 1 red_x_com [10:0] $end
$var reg 10 2 red_y_com [9:0] $end
$var reg 1 3 rst_in $end
$var reg 1 4 valid_blue $end
$var reg 1 5 valid_green $end
$var reg 1 6 valid_purple $end
$var reg 1 7 valid_red $end
$scope module uut $end
$var wire 1 * clk_in $end
$var wire 4 8 point_color [3:0] $end
$var wire 48 9 point_scalars [47:0] $end
$var wire 1 3 rst_in $end
$var wire 11 : x_origin [10:0] $end
$var wire 10 ; y_origin [9:0] $end
$var wire 48 < y_vec [47:0] $end
$var wire 48 = x_vec [47:0] $end
$var reg 4 > color_proj [3:0] $end
$var reg 3 ? index [2:0] $end
$var reg 32 @ x_proj [31:0] $end
$var reg 32 A y_proj [31:0] $end
$upscope $end
$scope module uut1 $end
$var wire 11 B blue_x_com [10:0] $end
$var wire 10 C blue_y_com [9:0] $end
$var wire 1 * clk_in $end
$var wire 11 D green_x_com [10:0] $end
$var wire 10 E green_y_com [9:0] $end
$var wire 11 F purple_x_com [10:0] $end
$var wire 10 G purple_y_com [9:0] $end
$var wire 11 H red_x_com [10:0] $end
$var wire 10 I red_y_com [9:0] $end
$var wire 1 3 rst_in $end
$var wire 1 4 valid_blue $end
$var wire 1 5 valid_green $end
$var wire 1 6 valid_purple $end
$var wire 1 7 valid_red $end
$var reg 48 J ball_vectors_x [47:0] $end
$var reg 48 K ball_vectors_y [47:0] $end
$var reg 11 L blue_x_stored [10:0] $end
$var reg 10 M blue_y_stored [9:0] $end
$var reg 11 N green_x_stored [10:0] $end
$var reg 10 O green_y_stored [9:0] $end
$var reg 1 P has_blue $end
$var reg 1 Q has_green $end
$var reg 1 R has_purple $end
$var reg 1 S has_red $end
$var reg 11 T purple_x_stored [10:0] $end
$var reg 10 U purple_y_stored [9:0] $end
$var reg 11 V red_x_stored [10:0] $end
$var reg 10 W red_y_stored [9:0] $end
$var integer 32 X state [31:0] $end
$upscope $end
$scope module uut2 $end
$var wire 1 * clk_in $end
$var wire 4 Y color_in [3:0] $end
$var wire 1 Z data_valid_in $end
$var wire 1 3 rst_in $end
$var wire 32 [ x_end_test [31:0] $end
$var wire 32 \ x_in [31:0] $end
$var wire 32 ] x_start_test [31:0] $end
$var wire 32 ^ y_end_test [31:0] $end
$var wire 32 _ y_in [31:0] $end
$var wire 32 ` y_start_test [31:0] $end
$var reg 4 a color [3:0] $end
$var reg 4 b color_end [3:0] $end
$var reg 32 c dx [31:0] $end
$var reg 32 d dy [31:0] $end
$var reg 32 e err [31:0] $end
$var reg 1 f has_first_point $end
$var reg 1 g next_point $end
$var reg 1 h sx $end
$var reg 1 i sy $end
$var reg 32 j x [31:0] $end
$var reg 32 k x_end [31:0] $end
$var reg 32 l x_start [31:0] $end
$var reg 32 m y [31:0] $end
$var reg 32 n y_end [31:0] $end
$var reg 32 o y_start [31:0] $end
$var integer 32 p state [31:0] $end
$upscope $end
$upscope $end
$enddefinitions $end
#0
$dumpvars
b0 p
bx o
bx n
bx m
bx l
bx k
bx j
xi
xh
xg
xf
bx e
bx d
bx c
bx b
bx a
bx `
bx _
bx ^
bx ]
bx \
bx [
1Z
bx Y
b0 X
bx W
bx V
bx U
bx T
xS
xR
xQ
xP
bx O
bx N
bx M
bx L
bx K
bx J
b0 I
b0 H
bx G
bx F
bx E
bx D
bx C
bx B
bx A
bx @
bx ?
bx >
bx =
bx <
b0 ;
b0 :
b110000000000000000000000000000000000000000 9
b1 8
x7
x6
x5
x4
03
b0 2
b0 1
bx 0
bx /
b110000000000000000000000000000000000000000 .
b1 -
bx ,
bx +
0*
bx )
bx (
bx '
bx &
bx %
bx $
bx #
bx "
bx !
$end
#5000
b1 %
b1 >
b1 Y
b1 p
1g
1*
#10000
0*
13
#15000
0g
0f
b0 p
b0 "
b0 m
b0 $
b0 j
b0 e
1i
1h
b0 d
b0 c
b0 %
b0 >
b0 Y
b0 !
b0 A
b0 _
b0 #
b0 @
b0 \
b0 ?
b0 &
b0 <
b0 K
b0 '
b0 =
b0 J
1*
#20000
0*
03
#25000
b1 %
b1 >
b1 Y
b0 a
b0 ^
b0 n
b0 [
b0 k
1f
1*
#30000
0*
b101011110 )
b101011110 C
b11111010 (
b11111010 B
b100101100 ,
b100101100 E
b110010000 +
b110010000 D
b11001000 0
b11001000 G
b100101100 /
b100101100 F
b100101100 2
b100101100 ;
b100101100 I
b100101100 1
b100101100 :
b100101100 H
16
15
17
14
#35000
bx a
b0 `
b0 o
b0 ]
b0 l
b1 b
b1 p
1g
b100101100 !
b100101100 A
b100101100 _
b100101100 #
b100101100 @
b100101100 \
1Q
b100101100 O
b110010000 N
1R
b11001000 U
b100101100 T
1P
b101011110 M
b11111010 L
1S
b100101100 W
b100101100 V
0i
0h
1*
#40000
0*
06
05
07
04
#45000
0S
0R
0P
0Q
b1 X
b0 p
0g
1*
#50000
0*
#55000
b1 a
b100101100 ^
b100101100 n
b100101100 [
b100101100 k
b1 p
1g
b111111111001110000000000001100100000000000000000 &
b111111111001110000000000001100100000000000000000 <
b111111111001110000000000001100100000000000000000 K
b11111111110011100000000001100100 '
b11111111110011100000000001100100 =
b11111111110011100000000001100100 J
b0 X
1i
b11111111111111111111111011010100 d
1h
b100101100 c
1*
#60000
0*
#65000
b0 !
b0 A
b0 _
b1 "
b1 m
b1 $
b1 j
0g
1*
#70000
0*
#75000
b10 "
b10 m
b10 $
b10 j
1*
#80000
0*
#85000
b11 "
b11 m
b11 $
b11 j
1*
#90000
0*
#95000
b100 "
b100 m
b100 $
b100 j
1*
#100000
0*
#105000
b101 "
b101 m
b101 $
b101 j
1*
#110000
0*
#115000
b110 "
b110 m
b110 $
b110 j
1*
#120000
0*
#125000
b111 "
b111 m
b111 $
b111 j
1*
#130000
0*
#135000
b1000 "
b1000 m
b1000 $
b1000 j
1*
#140000
0*
#145000
b1001 "
b1001 m
b1001 $
b1001 j
1*
#150000
0*
#155000
b1010 "
b1010 m
b1010 $
b1010 j
1*
#160000
0*
#165000
b1011 "
b1011 m
b1011 $
b1011 j
1*
#170000
0*
#175000
b1100 "
b1100 m
b1100 $
b1100 j
1*
#180000
0*
#185000
b1101 "
b1101 m
b1101 $
b1101 j
1*
#190000
0*
#195000
b1110 "
b1110 m
b1110 $
b1110 j
1*
#200000
0*
#205000
b1111 "
b1111 m
b1111 $
b1111 j
1*
#210000
0*
#215000
b10000 "
b10000 m
b10000 $
b10000 j
1*
#220000
0*
#225000
b10001 "
b10001 m
b10001 $
b10001 j
1*
#230000
0*
#235000
b10010 "
b10010 m
b10010 $
b10010 j
1*
#240000
0*
#245000
b10011 "
b10011 m
b10011 $
b10011 j
1*
#250000
0*
#255000
b10100 "
b10100 m
b10100 $
b10100 j
1*
#260000
0*
#265000
b10101 "
b10101 m
b10101 $
b10101 j
1*
#270000
0*
#275000
b10110 "
b10110 m
b10110 $
b10110 j
1*
#280000
0*
#285000
b10111 "
b10111 m
b10111 $
b10111 j
1*
#290000
0*
#295000
b11000 "
b11000 m
b11000 $
b11000 j
1*
#300000
0*
#305000
b11001 "
b11001 m
b11001 $
b11001 j
1*
#310000
0*
#315000
b11010 "
b11010 m
b11010 $
b11010 j
1*
#320000
0*
#325000
b11011 "
b11011 m
b11011 $
b11011 j
1*
#330000
0*
#335000
b11100 "
b11100 m
b11100 $
b11100 j
1*
#340000
0*
#345000
b11101 "
b11101 m
b11101 $
b11101 j
1*
#350000
0*
#355000
b11110 "
b11110 m
b11110 $
b11110 j
1*
#360000
0*
#365000
b11111 "
b11111 m
b11111 $
b11111 j
1*
#370000
0*
#375000
b100000 "
b100000 m
b100000 $
b100000 j
1*
#380000
0*
#385000
b100001 "
b100001 m
b100001 $
b100001 j
1*
#390000
0*
#395000
b100010 "
b100010 m
b100010 $
b100010 j
1*
#400000
0*
#405000
b100011 "
b100011 m
b100011 $
b100011 j
1*
#410000
0*
#415000
b100100 "
b100100 m
b100100 $
b100100 j
1*
#420000
0*
#425000
b100101 "
b100101 m
b100101 $
b100101 j
1*
#430000
0*
#435000
b100110 "
b100110 m
b100110 $
b100110 j
1*
#440000
0*
#445000
b100111 "
b100111 m
b100111 $
b100111 j
1*
#450000
0*
#455000
b101000 "
b101000 m
b101000 $
b101000 j
1*
#460000
0*
#465000
b101001 "
b101001 m
b101001 $
b101001 j
1*
#470000
0*
#475000
b101010 "
b101010 m
b101010 $
b101010 j
1*
#480000
0*
#485000
b101011 "
b101011 m
b101011 $
b101011 j
1*
#490000
0*
#495000
b101100 "
b101100 m
b101100 $
b101100 j
1*
#500000
0*
#505000
b101101 "
b101101 m
b101101 $
b101101 j
1*
#510000
0*
#515000
b101110 "
b101110 m
b101110 $
b101110 j
1*
#520000
0*
#525000
b101111 "
b101111 m
b101111 $
b101111 j
1*
#530000
0*
#535000
b110000 "
b110000 m
b110000 $
b110000 j
1*
#540000
0*
#545000
b110001 "
b110001 m
b110001 $
b110001 j
1*
#550000
0*
#555000
b110010 "
b110010 m
b110010 $
b110010 j
1*
#560000
0*
#565000
b110011 "
b110011 m
b110011 $
b110011 j
1*
#570000
0*
#575000
b110100 "
b110100 m
b110100 $
b110100 j
1*
#580000
0*
#585000
b110101 "
b110101 m
b110101 $
b110101 j
1*
#590000
0*
#595000
b110110 "
b110110 m
b110110 $
b110110 j
1*
#600000
0*
#605000
b110111 "
b110111 m
b110111 $
b110111 j
1*
#610000
0*
#615000
b111000 "
b111000 m
b111000 $
b111000 j
1*
#620000
0*
#625000
b111001 "
b111001 m
b111001 $
b111001 j
1*
#630000
0*
#635000
b111010 "
b111010 m
b111010 $
b111010 j
1*
#640000
0*
#645000
b111011 "
b111011 m
b111011 $
b111011 j
1*
#650000
0*
#655000
b111100 "
b111100 m
b111100 $
b111100 j
1*
#660000
0*
#665000
b111101 "
b111101 m
b111101 $
b111101 j
1*
#670000
0*
#675000
b111110 "
b111110 m
b111110 $
b111110 j
1*
#680000
0*
#685000
b111111 "
b111111 m
b111111 $
b111111 j
1*
#690000
0*
#695000
b1000000 "
b1000000 m
b1000000 $
b1000000 j
1*
#700000
0*
#705000
b1000001 "
b1000001 m
b1000001 $
b1000001 j
1*
#710000
0*
#715000
b1000010 "
b1000010 m
b1000010 $
b1000010 j
1*
#720000
0*
#725000
b1000011 "
b1000011 m
b1000011 $
b1000011 j
1*
#730000
0*
#735000
b1000100 "
b1000100 m
b1000100 $
b1000100 j
1*
#740000
0*
#745000
b1000101 "
b1000101 m
b1000101 $
b1000101 j
1*
#750000
0*
#755000
b1000110 "
b1000110 m
b1000110 $
b1000110 j
1*
#760000
0*
#765000
b1000111 "
b1000111 m
b1000111 $
b1000111 j
1*
#770000
0*
#775000
b1001000 "
b1001000 m
b1001000 $
b1001000 j
1*
#780000
0*
#785000
b1001001 "
b1001001 m
b1001001 $
b1001001 j
1*
#790000
0*
#795000
b1001010 "
b1001010 m
b1001010 $
b1001010 j
1*
#800000
0*
#805000
b1001011 "
b1001011 m
b1001011 $
b1001011 j
1*
#810000
0*
#815000
b1001100 "
b1001100 m
b1001100 $
b1001100 j
1*
#820000
0*
#825000
b1001101 "
b1001101 m
b1001101 $
b1001101 j
1*
#830000
0*
#835000
b1001110 "
b1001110 m
b1001110 $
b1001110 j
1*
#840000
0*
#845000
b1001111 "
b1001111 m
b1001111 $
b1001111 j
1*
#850000
0*
#855000
b1010000 "
b1010000 m
b1010000 $
b1010000 j
1*
#860000
0*
#865000
b1010001 "
b1010001 m
b1010001 $
b1010001 j
1*
#870000
0*
#875000
b1010010 "
b1010010 m
b1010010 $
b1010010 j
1*
#880000
0*
#885000
b1010011 "
b1010011 m
b1010011 $
b1010011 j
1*
#890000
0*
#895000
b1010100 "
b1010100 m
b1010100 $
b1010100 j
1*
#900000
0*
#905000
b1010101 "
b1010101 m
b1010101 $
b1010101 j
1*
#910000
0*
#915000
b1010110 "
b1010110 m
b1010110 $
b1010110 j
1*
#920000
0*
#925000
b1010111 "
b1010111 m
b1010111 $
b1010111 j
1*
#930000
0*
#935000
b1011000 "
b1011000 m
b1011000 $
b1011000 j
1*
#940000
0*
#945000
b1011001 "
b1011001 m
b1011001 $
b1011001 j
1*
#950000
0*
#955000
b1011010 "
b1011010 m
b1011010 $
b1011010 j
1*
#960000
0*
#965000
b1011011 "
b1011011 m
b1011011 $
b1011011 j
1*
#970000
0*
#975000
b1011100 "
b1011100 m
b1011100 $
b1011100 j
1*
#980000
0*
#985000
b1011101 "
b1011101 m
b1011101 $
b1011101 j
1*
#990000
0*
#995000
b1011110 "
b1011110 m
b1011110 $
b1011110 j
1*
#1000000
0*
#1005000
b1011111 "
b1011111 m
b1011111 $
b1011111 j
1*
#1010000
0*
#1015000
b1100000 "
b1100000 m
b1100000 $
b1100000 j
1*
#1020000
0*
#1025000
b1100001 "
b1100001 m
b1100001 $
b1100001 j
1*
#1030000
0*
#1035000
b1100010 "
b1100010 m
b1100010 $
b1100010 j
1*
#1040000
0*
#1045000
b1100011 "
b1100011 m
b1100011 $
b1100011 j
1*
#1050000
0*
#1055000
b1100100 "
b1100100 m
b1100100 $
b1100100 j
1*
#1060000
0*
#1065000
b1100101 "
b1100101 m
b1100101 $
b1100101 j
1*
#1070000
0*
#1075000
b1100110 "
b1100110 m
b1100110 $
b1100110 j
1*
#1080000
0*
#1085000
b1100111 "
b1100111 m
b1100111 $
b1100111 j
1*
#1090000
0*
#1095000
b1101000 "
b1101000 m
b1101000 $
b1101000 j
1*
#1100000
0*
#1105000
b1101001 "
b1101001 m
b1101001 $
b1101001 j
1*
#1110000
0*
#1115000
b1101010 "
b1101010 m
b1101010 $
b1101010 j
1*
#1120000
0*
#1125000
b1101011 "
b1101011 m
b1101011 $
b1101011 j
1*
#1130000
0*
#1135000
b1101100 "
b1101100 m
b1101100 $
b1101100 j
1*
#1140000
0*
#1145000
b1101101 "
b1101101 m
b1101101 $
b1101101 j
1*
#1150000
0*
#1155000
b1101110 "
b1101110 m
b1101110 $
b1101110 j
1*
#1160000
0*
#1165000
b1101111 "
b1101111 m
b1101111 $
b1101111 j
1*
#1170000
0*
#1175000
b1110000 "
b1110000 m
b1110000 $
b1110000 j
1*
#1180000
0*
#1185000
b1110001 "
b1110001 m
b1110001 $
b1110001 j
1*
#1190000
0*
#1195000
b1110010 "
b1110010 m
b1110010 $
b1110010 j
1*
#1200000
0*
#1205000
b1110011 "
b1110011 m
b1110011 $
b1110011 j
1*
#1210000
0*
#1215000
b1110100 "
b1110100 m
b1110100 $
b1110100 j
1*
#1220000
0*
#1225000
b1110101 "
b1110101 m
b1110101 $
b1110101 j
1*
#1230000
0*
#1235000
b1110110 "
b1110110 m
b1110110 $
b1110110 j
1*
#1240000
0*
#1245000
b1110111 "
b1110111 m
b1110111 $
b1110111 j
1*
#1250000
0*
#1255000
b1111000 "
b1111000 m
b1111000 $
b1111000 j
1*
#1260000
0*
#1265000
b1111001 "
b1111001 m
b1111001 $
b1111001 j
1*
#1270000
0*
#1275000
b1111010 "
b1111010 m
b1111010 $
b1111010 j
1*
#1280000
0*
#1285000
b1111011 "
b1111011 m
b1111011 $
b1111011 j
1*
#1290000
0*
#1295000
b1111100 "
b1111100 m
b1111100 $
b1111100 j
1*
#1300000
0*
#1305000
b1111101 "
b1111101 m
b1111101 $
b1111101 j
1*
#1310000
0*
#1315000
b1111110 "
b1111110 m
b1111110 $
b1111110 j
1*
#1320000
0*
#1325000
b1111111 "
b1111111 m
b1111111 $
b1111111 j
1*
#1330000
0*
#1335000
b10000000 "
b10000000 m
b10000000 $
b10000000 j
1*
#1340000
0*
#1345000
b10000001 "
b10000001 m
b10000001 $
b10000001 j
1*
#1350000
0*
#1355000
b10000010 "
b10000010 m
b10000010 $
b10000010 j
1*
#1360000
0*
#1365000
b10000011 "
b10000011 m
b10000011 $
b10000011 j
1*
#1370000
0*
#1375000
b10000100 "
b10000100 m
b10000100 $
b10000100 j
1*
#1380000
0*
#1385000
b10000101 "
b10000101 m
b10000101 $
b10000101 j
1*
#1390000
0*
#1395000
b10000110 "
b10000110 m
b10000110 $
b10000110 j
1*
#1400000
0*
#1405000
b10000111 "
b10000111 m
b10000111 $
b10000111 j
1*
#1410000
0*
#1415000
b10001000 "
b10001000 m
b10001000 $
b10001000 j
1*
#1420000
0*
#1425000
b10001001 "
b10001001 m
b10001001 $
b10001001 j
1*
#1430000
0*
#1435000
b10001010 "
b10001010 m
b10001010 $
b10001010 j
1*
#1440000
0*
#1445000
b10001011 "
b10001011 m
b10001011 $
b10001011 j
1*
#1450000
0*
#1455000
b10001100 "
b10001100 m
b10001100 $
b10001100 j
1*
#1460000
0*
#1465000
b10001101 "
b10001101 m
b10001101 $
b10001101 j
1*
#1470000
0*
#1475000
b10001110 "
b10001110 m
b10001110 $
b10001110 j
1*
#1480000
0*
#1485000
b10001111 "
b10001111 m
b10001111 $
b10001111 j
1*
#1490000
0*
#1495000
b10010000 "
b10010000 m
b10010000 $
b10010000 j
1*
#1500000
0*
#1505000
b10010001 "
b10010001 m
b10010001 $
b10010001 j
1*
